[
  {
    "bridgeContractAddress": "0x4F49866d47A086DdD7E54C8dE358Ef964a811794",
    "chainId": 31,
    "explorerUrl": "https://rootstock-testnet.blockscout.com",
    "icon": "https://strapi.mewapi.io/uploads/rootstock_large_d72adf1512_ee19a03096.png",
    "key": "ethereum",
    "name": "Rootstock",
    "nativeCurrency": {
      "decimals": 18,
      "logoUrl": "https://explorer.testnet.rootstock.io/assets/btc-orange.3ea0272f.svg",
      "name": "Rootstock Smart Bitcoin",
      "symbol": "RBTC"
    },
    "networkId": 0,
    "rpcUrl": "https://public-node.testnet.rsk.co",
    "rollupManagerAddress": "0xe3F11720a6c8e8c2ad1342DeD798e18319278341",
    "poeContractAddress": "0x8ffe6c5aBf7D3C0DE3b9f0CC91bD8DC97d65Ba92",
    "wrappedAddress": "0xB07FD1Dfbf55FB7c59018171b901D32f96801B31"
  },
  {
    "bridgeContractAddress": "0x6EfC2966a722218eb8D397d0Ca6a2AB20C3915Cd",
    "chainId": 1012,
    "explorerUrl": "https://explorer-testnet.biteigen.xyz",
    "icon": "https://raw.githubusercontent.com/BitEigen/brand-kit/main/logo/in-product/BitEigen_Logo.svg",
    "key": "polygon-zkevm",
    "name": "BitEigen",
    "nativeCurrency": {
      "decimals": 18,
      "logoUrl": "https://raw.githubusercontent.com/BitEigen/brand-kit/main/logo/in-product/BitEigen_Logo.svg",
      "name": "POL Token",
      "symbol": "POL"
    },
    "networkId": 1,
    "rpcUrl": "https://rpc-testnet.biteigen.xyz",
    "wrappedAddress": "0x746efa898c48383bd19513b559dFD1917C3038da"
  }
]
